[
	{
		//The id of the entity type to which the fields belongs
		"entity_id": 1,
		"fields":
		[
			{
				//The name of the field
				"fieldname": "firstname", 
				//The user created value
				"value": "Hans"
			},
			{
				"fieldname": "lastname", 
				"value": "Jensen"
			},
			{
				"fieldname": "birthplace",
				"value": "København", 
				//The id of the value. Relevant if the data comes from a typeahead field
				"id": "231287" 
			}
		],
		//Data from child entities
		"child_entities":
		[
			{
			"entity_id": 3,
			"fields":
				[
					{
						//The name of the field
						"fieldname": "position", 
						//The user created value
						"value": "Smed"
					}
				]
			},
			{
			"entity_id": 3,
			"fields":
				[
					{
						"fieldname": "position", 
						"value": "Arbejdsmand"
					}
				]
			}			
		]
	},
	{
		"entity_id": 2,
		"fields":
		[
			//Example of data after validation at server:
			{
				"fieldname": "firstname", 
				"value": "", 
				"id": null,
				"isValid" : false,
				"validation_message" : "Fornavn skal udfyldes"
			},
			{
				"fieldname": "lastname", 
				"value": "Nielsen", 
				"id": null,
				"isValid" : true,
				"validation_message" : null
			}
		]
	},	
	{
		"entity_id": 2,
		"fields":
		[
			{
				"fieldname": "firstname", 
				"value": "Hans", 
				"id": null
			},
			{
				"fieldname": "lastname", 
				"value": "Frandsen", 
				"id": null
			}
		]
	}	
]
